bamt/__init__.py
bamt/builders/__init__.py
bamt/builders/builders_base.py
bamt/builders/composite_builder.py
bamt/builders/evo_builder.py
bamt/builders/hc_builder.py
bamt/display/__init__.py
bamt/display/display.py
bamt/external/__init__.py
bamt/external/pyBN/__init__.py
bamt/external/pyBN/classes/__init__.py
bamt/external/pyBN/classes/_tests/__init__.py
bamt/external/pyBN/classes/_tests/test_bayesnet.py
bamt/external/pyBN/classes/bayesnet.py
bamt/external/pyBN/utils/__init__.py
bamt/external/pyBN/utils/_tests/__init__.py
bamt/external/pyBN/utils/_tests/test_independence_tests.py
bamt/external/pyBN/utils/_tests/test_markov_blanket.py
bamt/external/pyBN/utils/_tests/test_orient_edges.py
bamt/external/pyBN/utils/_tests/test_random_sample.py
bamt/external/pyBN/utils/class_equivalence.py
bamt/external/pyBN/utils/data.py
bamt/external/pyBN/utils/graph.py
bamt/external/pyBN/utils/independence_tests.py
bamt/external/pyitlib/DiscreteRandomVariableUtils.py
bamt/external/pyitlib/__init__.py
bamt/log.py
bamt/logging.conf
bamt/mi_entropy_gauss.py
bamt/networks/__init__.py
bamt/networks/base.py
bamt/networks/big_brave_bn.py
bamt/networks/composite_bn.py
bamt/networks/continuous_bn.py
bamt/networks/discrete_bn.py
bamt/networks/hybrid_bn.py
bamt/nodes/__init__.py
bamt/nodes/base.py
bamt/nodes/composite_continuous_node.py
bamt/nodes/composite_discrete_node.py
bamt/nodes/conditional_gaussian_node.py
bamt/nodes/conditional_logit_node.py
bamt/nodes/conditional_mixture_gaussian_node.py
bamt/nodes/discrete_node.py
bamt/nodes/gaussian_node.py
bamt/nodes/logit_node.py
bamt/nodes/mixture_gaussian_node.py
bamt/nodes/schema.py
bamt/preprocess/__init__.py
bamt/preprocess/discretization.py
bamt/preprocess/graph.py
bamt/preprocess/numpy_pandas.py
bamt/preprocessors.py
bamt/redef_HC.py
bamt/redef_info_scores.py
bamt/result_models/__init__.py
bamt/result_models/node_result.py
bamt/result_models/results.py
bamt/utils/EvoUtils.py
bamt/utils/GraphUtils.py
bamt/utils/MathUtils.py
bamt-1.3.0.dist-info/LICENCE
bamt-1.3.0.dist-info/METADATA
bamt-1.3.0.dist-info/WHEEL
bamt-1.3.0.dist-info/RECORD
