Metadata-Version: 2.1
Name: BAMT
Version: 1.3.0
Summary: data modeling and analysis tool based on Bayesian networks
Home-page: https://github.com/ITMO-NSS-team/BAMT
License: BSD-3-Clause
Author: Roman Netrogolov
Author-email: romius2001@gmail.com
Requires-Python: >=3.9
Classifier: Development Status :: 3 - Alpha
Classifier: License :: OSI Approved :: BSD License
Classifier: Programming Language :: Python :: 3
Classifier: Programming Language :: Python :: 3.9
Classifier: Programming Language :: Python :: 3.10
Classifier: Programming Language :: Python :: 3.11
Classifier: Programming Language :: Python :: 3.12
Classifier: Programming Language :: Python :: 3.13
Classifier: Topic :: Scientific/Engineering :: Mathematics
Provides-Extra: composite-extras
Requires-Dist: catboost (>=1.0.6)
Requires-Dist: gmr (==1.6.2)
Requires-Dist: lightgbm (>=3.3.5) ; extra == "composite-extras"
Requires-Dist: matplotlib (>=3.6.2,<4.0.0)
Requires-Dist: missingno (>=0.5.1,<0.6.0)
Requires-Dist: numpy (>=1.26.4)
Requires-Dist: pandas (>=2.0.3)
Requires-Dist: pgmpy (>=1.0.0)
Requires-Dist: pyvis (>=0.2.1)
Requires-Dist: scikit-learn (>=1.2.0,<2.0.0)
Requires-Dist: scipy (>=1.8.0,<2.0.0)
Requires-Dist: thegolem (>=0.3.3)
Requires-Dist: xgboost (>=1.7.6)
Project-URL: Repository, https://github.com/ITMO-NSS-team/BAMT
